atccondition/__init__.py
atccondition/atccondition.py
atccondition/http_calls.py
atccondition-0.6.dist-info/LICENSE
atccondition-0.6.dist-info/METADATA
atccondition-0.6.dist-info/WHEEL
atccondition-0.6.dist-info/top_level.txt
atccondition-0.6.dist-info/RECORD
