Metadata-Version: 2.1
Name: atccondition
Version: 0.6
Summary: A Pip Package for Akamai Test Center Condition
Home-page: https://github.com/Achuthananda/AkamaiTestCondition
Author: Achuthananda M P
Author-email: achuthadivine@gmail.com
License: UNKNOWN
Platform: UNKNOWN
Classifier: Programming Language :: Python :: 3
Classifier: License :: OSI Approved :: MIT License
Classifier: Operating System :: OS Independent
